amapy_utils/__init__.py
amapy_utils/common/__init__.py
amapy_utils/common/better_set.py
amapy_utils/common/class_property.py
amapy_utils/common/exceptions.py
amapy_utils/common/singleton.py
amapy_utils/common/user_commands.py
amapy_utils/common/user_messages.py
amapy_utils/common/tests/__init__.py
amapy_utils/common/tests/test_better_set.py
amapy_utils/common/tests/test_class_property.py
amapy_utils/common/tests/test_singleton.py
amapy_utils/utils/__init__.py
amapy_utils/utils/aws_hash.py
amapy_utils/utils/cloud_utils.py
amapy_utils/utils/file_html_diff.py
amapy_utils/utils/file_tree.py
amapy_utils/utils/file_utils.py
amapy_utils/utils/in_memory_file.py
amapy_utils/utils/in_memory_zip.py
amapy_utils/utils/log_utils.py
amapy_utils/utils/pager.py
amapy_utils/utils/path_utils.py
amapy_utils/utils/progress.py
amapy_utils/utils/stat_utils.py
amapy_utils/utils/utils.py
amapy_utils/utils/web_utils.py
amapy_utils/utils/tests/__init__.py
amapy_utils/utils/tests/test_aws_hash.py
amapy_utils/utils/tests/test_cloud_utils.py
amapy_utils/utils/tests/test_file_tree.py
amapy_utils/utils/tests/test_file_utils.py
amapy_utils/utils/tests/test_in_memory_file.py
amapy_utils/utils/tests/test_log_utils.py
amapy_utils/utils/tests/test_path_utils.py
amapy_utils/utils/tests/test_progress.py
amapy_utils/utils/tests/test_utils.py
amapy_utils-1.0.1.dist-info/METADATA
amapy_utils-1.0.1.dist-info/WHEEL
amapy_utils-1.0.1.dist-info/top_level.txt
amapy_utils-1.0.1.dist-info/RECORD
